flextable/__init__.py
flextable/align.py
flextable/base_container.py
flextable/cell.py
flextable/cells_container.py
flextable/column.py
flextable/columns_container.py
flextable/const.py
flextable/exceptions.py
flextable/row.py
flextable/rows_container.py
flextable/separator.py
flextable/table.py
flextable/renderers/__init__.py
flextable/renderers/ascii_table_renderer.py
flextable/renderers/context.py
flextable/renderers/contracts.py
flextable/renderers/fancy_renderer.py
flextable/renderers/ms_dos_renderer.py
flextable/renderers/plus_minus_renderer.py
tests/__init__.py
tests/base_test_case.py
tests/renderers_test.py
tests/table_test.py
flex_text_table-2.7.0.dist-info/LICENSE.md
flex_text_table-2.7.0.dist-info/METADATA
flex_text_table-2.7.0.dist-info/WHEEL
flex_text_table-2.7.0.dist-info/top_level.txt
flex_text_table-2.7.0.dist-info/RECORD
