Metadata-Version: 2.1
Name: flex-text-table
Version: 2.7.0
Summary: Fast and flexible Pyhon library for text tables.
Home-page: https://github.com/MarcinOrlowski/python-flex-text-table/
Author: Marcin Orlowski
Author-email: mail@marcinOrlowski.com
License: MIT License
Project-URL: Bug Tracker, https://github.com/MarcinOrlowski/python-flex-table/issues/
Project-URL: Documentation, https://github.com/MarcinOrlowski/python-flex-table/
Project-URL: Source Code, https://github.com/MarcinOrlowski/python-flex-table/
Keywords: text table ascii command line console shell cli utf8 unicode
Classifier: Programming Language :: Python :: 3
Classifier: License :: OSI Approved :: MIT License
Classifier: Operating System :: OS Independent
Requires-Python: >=3.8
License-File: LICENSE.md
